{
  "sections": [
    {
      "year": 2025,
      "items": [
        {
          "id": "2025-1",
          "type": "image",
          "title": "Venezuelan Night",
          "src": "VA Images/Posters&Flyers/2025/2025-venezuelan-night.jpg",
          "alt": "2025 Venezuelan Night",
          "link": "/2025/VenezuelanNight"
        },
        {
          "id": "2025-last",
          "type": "text",
          "title": "Milestones",
          "text": "Here is a text box",
          "variant": "boxed",
          "link": ""
        }
      ]
    },
    {
      "year": 2024,
      "items": [
        {
          "id": "2024-1",
          "type": "image",
          "title": "Eve of Nations",
          "src": "VA Images/Posters&Flyers/2024/2024-eon.jpg",
          "alt": "2024 Eve of Nations",
          "link": "/2024/EveOfNations"
        },
        {
          "id": "2024-2",
          "type": "image",
          "title": "Venezuelan Night",
          "src": "VA Images/Posters&Flyers/2024/2024-venezuelan-night.JPG",
          "alt": "2024 Venezuelan Night",
          "link": "/2024/VenezuelanNight"
        },
        {
          "id": "2024-3",
          "type": "image",
          "title": "Backyard Grill",
          "src": "VA Images/Posters&Flyers/2024/2024-backyard-grill.jpg",
          "alt": "2024 Backyard Grill",
          "link": "/2024/BackyardGrill"
        },
        {
          "id": "2024-4",
          "type": "image",
          "title": "Fiestas de las Americas",
          "src": "VA Images/Posters&Flyers/2024/2024-fiestas-de-las-americas.jpg",
          "alt": "2024 Fiestas de las Americas",
          "link": "/2024/FiestasDeLasAmericas"
        },
        {
          "id": "2024-5",
          "type": "image",
          "title": "Arepada",
          "src": "VA Images/Posters&Flyers/2024/2024-arepada.jpg",
          "alt": "2024 Arepada",
          "link": "/2024/Arepada"
        },
        {
          "id": "2024-6",
          "type": "image",
          "title": "Simon Movie Night",
          "src": "VA Images/Posters&Flyers/2024/2024-simon-movie-night.jpg",
          "alt": "2024 Simon Movie Night",
          "link": "/2024/SimonMovieNight"
        },
        {
          "id": "2024-7",
          "type": "image",
          "title": "Noche de Gaita",
          "src": "VA Images/Posters&Flyers/2024/2024-noche-de-gaita.jpg",
          "alt": "2024 Noche de Gaita",
          "link": "/2024/NocheDeGaita"
        },
        {
          "id": "2024-8",
          "type": "text",
          "title": "Milestones",
          "text": "Here is a text box",
          "variant": "boxed",
          "link": ""
        }
      ]
    },
    {
      "year": 2023,
      "items": [
        {
          "id": "2023-1",
          "type": "image",
          "title": "Venezuelan Night",
          "src": "VA Images/Posters&Flyers/2023/2023-venezuelan-night.jpg",
          "alt": "2023 Venezuelan Night",
          "link": "/2023/VenezuelanNight"
        },
        {
          "id": "2023-2",
          "type": "image",
          "title": "Arepada & Game Night",
          "src": "VA Images/Posters&Flyers/2023/2023-arepada-and-game-night.jpg",
          "alt": "2023 Arepada and Game Night",
          "link": "/2023/ArepadaGameNight"
        },
        {
          "id": "2023-3",
          "type": "image",
          "title": "Backyard Grill",
          "src": "VA Images/Posters&Flyers/2023/2023-backyard-grill-with-afv.jpg",
          "alt": "2023 Backyard Grill",
          "link": "/2023/BackyardGrill"
        },
        {
          "id": "2023-4",
          "type": "image",
          "title": "Arepada",
          "src": "VA Images/Posters&Flyers/2023/2023-arepada.jpg",
          "alt": "2023 Arepada",
          "link": "/2023/Arepada"
        },
        {
          "id": "2023-5",
          "type": "image",
          "title": "Boys & Girls Club Show",
          "src": "VA Images/Posters&Flyers/2023/2023-boys-and-girls-club-show.JPG",
          "alt": "2023 Boys and Girls Club Show",
          "link": "/2023/BoysGirlsClubShow"
        },
        {
          "id": "2023-6",
          "type": "image",
          "title": "Noche de Gaita",
          "src": "VA Images/Posters&Flyers/2023/2023-noche-de-gaita.jpg",
          "alt": "2023 Noche de Gaita",
          "link": "/2023/NocheDeGaita"
        },
        {
          "id": "2023-7",
          "type": "text",
          "title": "Milestones",
          "text": "Here is a text box",
          "variant": "boxed",
          "link": ""
        }
      ]
    },
    {
      "year": 2022,
      "items": [
        {
          "id": "2022-1",
          "type": "image",
          "title": "Backyard Grill",
          "src": "VA Images/Posters&Flyers/2022/2022-backyard-grill.jpg",
          "alt": "2022 Backyard Grill",
          "link": "/2022/BackyardGrill"
        },
        {
          "id": "2022-2",
          "type": "image",
          "title": "Venezuelan Night",
          "src": "VA Images/Posters&Flyers/2022/2022-venezuelan-night.jpg",
          "alt": "2022 Venezuelan Night",
          "link": "/2022/VenezuelanNight"
        },
        {
          "id": "2022-3",
          "type": "image",
          "title": "BBQ Party & Game Night",
          "src": "VA Images/Posters&Flyers/2022/2022-bbq-party-and-game-night.jpg",
          "alt": "2022 BBQ Party and Game Night",
          "link": "/2022/BBQPartyGameNight"
        },
        {
          "id": "2022-4",
          "type": "image",
          "title": "COLSA & AFV Cultural Night",
          "src": "VA Images/Posters&Flyers/2022/2022-colsa-and-afv-cultural-night.jpg",
          "alt": "2022 COLSA and AFV Cultural Night",
          "link": "/2022/COLSAAFVCulturalNight"
        },
        {
          "id": "2022-5",
          "type": "image",
          "title": "Hallacada",
          "src": "VA Images/Posters&Flyers/2022/2022-hallacada.jpg",
          "alt": "2022 Hallacada",
          "link": "/2022/Hallacada"
        },
        {
          "id": "2024-8",
          "type": "text",
          "title": "Milestones",
          "text": "Here is a text box",
          "variant": "boxed",
          "link": ""
        }
      ]
    },
    {
      "year": 2021,
      "items": [
        {
          "id": "2021-1",
          "type": "image",
          "title": "Backyard Grill",
          "src": "VA Images/Posters&Flyers/2021/2021-backyard-grill.jpg",
          "alt": "2021 Backyard Grill",
          "link": "/2021/BackyardGrill"
        },
        {
          "id": "2021-2",
          "type": "image",
          "title": "Arepa & Game Night",
          "src": "VA Images/Posters&Flyers/2021/2021-arepa-and-game-night.jpg",
          "alt": "2021 Arepa and Game Night",
          "link": "/2021/ArepaGameNight"
        },
        {
          "id": "2021-3",
          "type": "image",
          "title": "Open Mic",
          "src": "VA Images/Posters&Flyers/2021/2021-open-mic.jpg",
          "alt": "2021 Open Mic",
          "link": "/2021/OpenMic"
        },
        {
          "id": "2024-4",
          "type": "text",
          "title": "Milestones",
          "text": "Here is a text box",
          "variant": "boxed",
          "link": ""
        }
      ]
    },
    {
      "year": 2019,
      "items": [
        {
          "id": "2019-1",
          "type": "image",
          "title": "Venezuelan Night",
          "src": "VA Images/Posters&Flyers/2019/2019-venezuelan-night.png",
          "alt": "2019 Venezuelan Night",
          "link": "/2019/VenezuelanNight"
        },
        {
          "id": "2019-2",
          "type": "image",
          "title": "Venezuelan Night",
          "src": "VA Images/Posters&Flyers/2019/2019-noche-gaitera.jpg",
          "alt": "2019 Venezuelan Night",
          "link": "/2019/VenezuelanNight"
        },
        {
          "id": "2024-3",
          "type": "text",
          "title": "Milestones",
          "text": "Here is a text box",
          "variant": "boxed",
          "link": ""
        }
      ]
    },
    {
      "year": 2018,
      "items": [
        {
          "id": "2018-1",
          "type": "image",
          "title": "Venezuelan Night",
          "src": "VA Images/Posters&Flyers/2018/2018-venezuelan-night.jpg",
          "alt": "2018 Venezuelan Night",
          "link": "/2018/VenezuelanNight"
        },
        {
          "id": "2018-2",
          "type": "image",
          "title": "Feria Gaitera",
          "src": "VA Images/Posters&Flyers/2018/2018-noche-gaitera.jpg",
          "alt": "2018 Feria Gaitera",
          "link": "/2018/FeriaGaitera"
        },
        {
          "id": "2024-3",
          "type": "text",
          "title": "Milestones",
          "text": "Here is a text box",
          "variant": "boxed",
          "link": ""
        }
      ]
    },
    {
      "year": 2017,
      "items": [
        {
          "id": "2017-1",
          "type": "image",
          "title": "Venezuelan Night",
          "src": "VA Images/Posters&Flyers/2017/2017-venezuelan-night.jpg",
          "alt": "2017 Venezuelan Night",
          "link": "/2017/VenezuelanNight"
        },
        {
          "id": "2017-2",
          "type": "image",
          "title": "Soonerthon",
          "src": "VA Images/Posters&Flyers/2017/2017-soonerthon.jpg",
          "alt": "2017 Soonerthon",
          "link": "/2017/Soonerthon"
        },
        {
          "id": "2017-3",
          "type": "image",
          "title": "Arepazo",
          "src": "VA Images/Posters&Flyers/2017/2017-arepazo.jpg",
          "alt": "2017 Arepaz",
          "link": "/2017/Arepazo"
        },
        {
          "id": "2017-4",
          "type": "image",
          "title": "International Bazaar",
          "src": "VA Images/Posters&Flyers/2017/2017-international-bazaar.jpg",
          "alt": "2017 International Bazaar",
          "link": "/2017/InternationalBazaar"
        },
        {
          "id": "2017-5",
          "type": "image",
          "title": "Feria Gaitera",
          "src": "VA Images/Posters&Flyers/2017/2017-noche-gaitera.jpg",
          "alt": "2017 Feria Gaitera",
          "link": "/2017/FeriaGaitera"
        },
        {
          "id": "2024-6",
          "type": "text",
          "title": "Milestones",
          "text": "Here is a text box",
          "variant": "boxed",
          "link": ""
        }
      ]
    },
    {
      "year": 2014,
      "items": [
        {
          "id": "2014-1",
          "type": "image",
          "title": "Venezuelan Night",
          "src": "VA Images/Posters&Flyers/2014-venezuelan-night.jpg",
          "alt": "2014 Venezuelan Night",
          "link": "/2014/VenezuelanNight"
        },
        {
          "id": "2024-2",
          "type": "text",
          "title": "Milestones",
          "text": "Here is a text box",
          "variant": "boxed",
          "link": ""
        }
      ]
    },
    {
      "year": 2006,
      "items": [
        {
          "id": "2006-1",
          "type": "image",
          "title": "Pabellon Dinner",
          "src": "VA Images/Posters&Flyers/2006-pabellon-dinner.jpg",
          "alt": "2006 Pabellon Dinner",
          "link": "/2006/PabellonDinner"
        },
        {
          "id": "2006-2",
          "type": "image",
          "title": "Gaitazo",
          "src": "VA Images/Posters&Flyers/2006-gaitazo.jpg",
          "alt": "2006 Gaitazo",
          "link": "/2006/Gaitazo"
        },
        {
          "id": "2024-3",
          "type": "text",
          "title": "Milestones",
          "text": "Here is a text box",
          "variant": "boxed",
          "link": ""
        }
      ]
    },
    {
      "year": 2005,
      "items": [
        {
          "id": "2005-1",
          "type": "image",
          "title": "Panam Night",
          "src": "VA Images/Posters&Flyers/2005-panam-night.jpg",
          "alt": "2005 Panam Night",
          "link": "/2005/PanamNight"
        },
        {
          "id": "2024-2",
          "type": "text",
          "title": "Milestones",
          "text": "Here is a text box",
          "variant": "boxed",
          "link": ""
        }
      ]
    },
    {
      "year": 2004,
      "items": [
        {
          "id": "2004-1",
          "type": "image",
          "title": "Feria de la Chinita",
          "src": "VA Images/Posters&Flyers/2004-feria-de-la-chinita.jpg",
          "alt": "Feria de la Chinita 2004",
          "link": "/2004/FeriaDeLaChinita"
        },
        {
          "id": "2024-2",
          "type": "text",
          "title": "Milestones",
          "text": "Here is a text box",
          "variant": "boxed",
          "link": ""
        }
      ]
    }
  ]
}
